{
    "asset": {
        "format": "jpg",
        "id": "ja_lili_men_chapter_24_08_png_jpg.rf.8408cf132a80603e4677bf2cb9d9f28d",
        "name": "ja_lili_men_chapter_24_08_png_jpg.rf.8408cf132a80603e4677bf2cb9d9f28d.jpg",
        "path": "file:C:\\Users\\asus\\source\\repos\\MangaKB\\MangaKB\\MangaDataS\\vott-json-export\\ja_lili_men_chapter_24_08_png_jpg.rf.8408cf132a80603e4677bf2cb9d9f28d.jpg",
        "size": {
            "width": 512,
            "height": 728
        },
        "state": 2,
        "type": 1
    },
    "regions": [
        {
            "id": "Ju01RBdo6a",
            "type": "RECTANGLE",
            "tags": [
                "text_bubble"
            ],
            "boundingBox": {
                "left": 130.83939662821652,
                "top": 22.75,
                "width": 79.50310559006212,
                "height": 108.0625
            },
            "points": [
                {
                    "x": 130.83939662821652,
                    "y": 22.75
                },
                {
                    "x": 210.3425022182786,
                    "y": 22.75
                },
                {
                    "x": 210.3425022182786,
                    "y": 130.8125
                },
                {
                    "x": 130.83939662821652,
                    "y": 130.8125
                }
            ]
        },
        {
            "id": "fkFkSxeBYZU",
            "type": "RECTANGLE",
            "tags": [
                "text_bubble"
            ],
            "boundingBox": {
                "height": 101.2375,
                "width": 89.9458618468233,
                "left": 112.21917808219179,
                "top": 127.4
            },
            "points": [
                {
                    "x": 112.21917808219179,
                    "y": 127.4
                },
                {
                    "x": 202.16503992901508,
                    "y": 127.4
                },
                {
                    "x": 202.16503992901508,
                    "y": 228.63750000000002
                },
                {
                    "x": 112.21917808219179,
                    "y": 228.63750000000002
                }
            ]
        },
        {
            "id": "YFb_slexPwD",
            "type": "RECTANGLE",
            "tags": [
                "text_bubble"
            ],
            "boundingBox": {
                "height": 125.46756756756758,
                "width": 77.23158828748889,
                "left": 385.2493345164153,
                "top": 100.1
            },
            "points": [
                {
                    "x": 385.2493345164153,
                    "y": 100.1
                },
                {
                    "x": 462.48092280390415,
                    "y": 100.1
                },
                {
                    "x": 462.48092280390415,
                    "y": 225.56756756756758
                },
                {
                    "x": 385.2493345164153,
                    "y": 225.56756756756758
                }
            ]
        },
        {
            "id": "kvGPEVIwMvn",
            "type": "RECTANGLE",
            "tags": [
                "text_bubble"
            ],
            "boundingBox": {
                "left": 105.85270629991128,
                "top": 238.875,
                "width": 103.35403726708076,
                "height": 122.85000000000001
            },
            "points": [
                {
                    "x": 105.85270629991128,
                    "y": 238.875
                },
                {
                    "x": 209.20674356699203,
                    "y": 238.875
                },
                {
                    "x": 209.20674356699203,
                    "y": 361.725
                },
                {
                    "x": 105.85270629991128,
                    "y": 361.725
                }
            ]
        },
        {
            "id": "Hti0fIIXPqd",
            "type": "RECTANGLE",
            "tags": [
                "text_bubble"
            ],
            "boundingBox": {
                "height": 58.012499999999996,
                "width": 85.18189884649512,
                "left": 84.00631085072504,
                "top": 521.2683783783782
            },
            "points": [
                {
                    "x": 84.00631085072504,
                    "y": 521.2683783783782
                },
                {
                    "x": 169.1882096972202,
                    "y": 521.2683783783782
                },
                {
                    "x": 169.1882096972202,
                    "y": 579.2808783783781
                },
                {
                    "x": 84.00631085072504,
                    "y": 579.2808783783781
                }
            ]
        },
        {
            "id": "q8PQ9SzqNTO",
            "type": "RECTANGLE",
            "tags": [
                "text_bubble"
            ],
            "boundingBox": {
                "height": 121.23378378378385,
                "width": 82.217724350014,
                "left": 53.304109589041104,
                "top": 549.1445945945945
            },
            "points": [
                {
                    "x": 53.304109589041104,
                    "y": 549.1445945945945
                },
                {
                    "x": 135.52183393905509,
                    "y": 549.1445945945945
                },
                {
                    "x": 135.52183393905509,
                    "y": 670.3783783783784
                },
                {
                    "x": 53.304109589041104,
                    "y": 670.3783783783784
                }
            ]
        },
        {
            "id": "vdZt2vTySs2",
            "type": "RECTANGLE",
            "tags": [
                "text_bubble"
            ],
            "boundingBox": {
                "height": 118.30000000000003,
                "width": 65.22739726027397,
                "left": 24.547945205479454,
                "top": 589.5675675675675
            },
            "points": [
                {
                    "x": 24.547945205479454,
                    "y": 589.5675675675675
                },
                {
                    "x": 89.77534246575343,
                    "y": 589.5675675675675
                },
                {
                    "x": 89.77534246575343,
                    "y": 707.8675675675676
                },
                {
                    "x": 24.547945205479454,
                    "y": 707.8675675675676
                }
            ]
        },
        {
            "id": "NaW-0Z_vj0G",
            "type": "RECTANGLE",
            "tags": [
                "text_bubble"
            ],
            "boundingBox": {
                "height": 97.82499999999999,
                "width": 57.73139016178241,
                "left": 256.4823084683546,
                "top": 605.8122972972973
            },
            "points": [
                {
                    "x": 256.4823084683546,
                    "y": 605.8122972972973
                },
                {
                    "x": 314.213698630137,
                    "y": 605.8122972972973
                },
                {
                    "x": 314.213698630137,
                    "y": 703.6372972972973
                },
                {
                    "x": 256.4823084683546,
                    "y": 703.6372972972973
                }
            ]
        },
        {
            "id": "FyJB3jxDYSw",
            "type": "RECTANGLE",
            "tags": [
                "text_bubble"
            ],
            "boundingBox": {
                "left": 205.7994676131322,
                "top": 625.625,
                "width": 61.33096716947649,
                "height": 97.825
            },
            "points": [
                {
                    "x": 205.7994676131322,
                    "y": 625.625
                },
                {
                    "x": 267.1304347826087,
                    "y": 625.625
                },
                {
                    "x": 267.1304347826087,
                    "y": 723.45
                },
                {
                    "x": 205.7994676131322,
                    "y": 723.45
                }
            ]
        },
        {
            "id": "AOp8dQiCVoB",
            "type": "RECTANGLE",
            "tags": [
                "text_bubble"
            ],
            "boundingBox": {
                "height": 142.17081081081085,
                "width": 85.51173560549888,
                "left": 196.38356164383563,
                "top": 458.63999999999993
            },
            "points": [
                {
                    "x": 196.38356164383563,
                    "y": 458.63999999999993
                },
                {
                    "x": 281.89529724933453,
                    "y": 458.63999999999993
                },
                {
                    "x": 281.89529724933453,
                    "y": 600.8108108108107
                },
                {
                    "x": 196.38356164383563,
                    "y": 600.8108108108107
                }
            ]
        },
        {
            "id": "vUQ09ZlSlrT",
            "type": "RECTANGLE",
            "tags": [
                "text_bubble"
            ],
            "boundingBox": {
                "height": 117.16250000000001,
                "width": 79.65806663344313,
                "left": 205.7994676131322,
                "top": 236.6
            },
            "points": [
                {
                    "x": 205.7994676131322,
                    "y": 236.6
                },
                {
                    "x": 285.4575342465754,
                    "y": 236.6
                },
                {
                    "x": 285.4575342465754,
                    "y": 353.7625
                },
                {
                    "x": 205.7994676131322,
                    "y": 353.7625
                }
            ]
        },
        {
            "id": "VXSzbqQvmDf",
            "type": "RECTANGLE",
            "tags": [
                "text_bubble"
            ],
            "boundingBox": {
                "height": 83.12972972972973,
                "width": 72.68855368234249,
                "left": 415.68766637089624,
                "top": 236.6
            },
            "points": [
                {
                    "x": 415.68766637089624,
                    "y": 236.6
                },
                {
                    "x": 488.3762200532387,
                    "y": 236.6
                },
                {
                    "x": 488.3762200532387,
                    "y": 319.72972972972974
                },
                {
                    "x": 415.68766637089624,
                    "y": 319.72972972972974
                }
            ]
        }
    ],
    "version": "2.2.0"
}