{
    "asset": {
        "format": "jpg",
        "id": "ja_lili_men_chapter_9_07_png_jpg.rf.b42302767b4430b4f4ca93f427b5f3aa",
        "name": "ja_lili_men_chapter_9_07_png_jpg.rf.b42302767b4430b4f4ca93f427b5f3aa.jpg",
        "path": "file:C:\\Users\\asus\\source\\repos\\MangaKB\\MangaKB\\MangaDataS\\vott-json-export\\ja_lili_men_chapter_9_07_png_jpg.rf.b42302767b4430b4f4ca93f427b5f3aa.jpg",
        "size": {
            "width": 1127,
            "height": 1600
        },
        "state": 2,
        "type": 1
    },
    "regions": [
        {
            "id": "wSZwYQ-D65",
            "type": "RECTANGLE",
            "tags": [
                "shout_bubble"
            ],
            "boundingBox": {
                "height": 271.8455598455599,
                "width": 215,
                "left": 168,
                "top": 88
            },
            "points": [
                {
                    "x": 168,
                    "y": 88
                },
                {
                    "x": 383,
                    "y": 88
                },
                {
                    "x": 383,
                    "y": 359.8455598455599
                },
                {
                    "x": 168,
                    "y": 359.8455598455599
                }
            ]
        },
        {
            "id": "CZfJTr48JMP",
            "type": "RECTANGLE",
            "tags": [
                "shout_bubble"
            ],
            "boundingBox": {
                "height": 263.8803088803089,
                "width": 221.78493150684932,
                "left": 70,
                "top": 445
            },
            "points": [
                {
                    "x": 70,
                    "y": 445
                },
                {
                    "x": 291.7849315068493,
                    "y": 445
                },
                {
                    "x": 291.7849315068493,
                    "y": 708.8803088803089
                },
                {
                    "x": 70,
                    "y": 708.8803088803089
                }
            ]
        }
    ],
    "version": "2.2.0"
}