{
    "asset": {
        "format": "jpg",
        "id": "ja_one_punch_man_chapter_12_01_png_jpg.rf.3afc1c82b39a2cf9f0f726c43bec249f",
        "name": "ja_one_punch_man_chapter_12_01_png_jpg.rf.3afc1c82b39a2cf9f0f726c43bec249f.jpg",
        "path": "file:C:\\Users\\asus\\source\\repos\\MangaKB\\MangaKB\\MangaDataS\\vott-json-export\\ja_one_punch_man_chapter_12_01_png_jpg.rf.3afc1c82b39a2cf9f0f726c43bec249f.jpg",
        "size": {
            "width": 996,
            "height": 1600
        },
        "state": 2,
        "type": 1
    },
    "regions": [
        {
            "id": "N96azf54xM",
            "type": "RECTANGLE",
            "tags": [
                "shout_bubble"
            ],
            "boundingBox": {
                "height": 627.0270270270271,
                "width": 384.9023255813953,
                "left": 188.39069767441862,
                "top": 0
            },
            "points": [
                {
                    "x": 188.39069767441862,
                    "y": 0
                },
                {
                    "x": 573.2930232558139,
                    "y": 0
                },
                {
                    "x": 573.2930232558139,
                    "y": 627.0270270270271
                },
                {
                    "x": 188.39069767441862,
                    "y": 627.0270270270271
                }
            ]
        },
        {
            "id": "1_JKg1z1QhW",
            "type": "RECTANGLE",
            "tags": [
                "shout_bubble"
            ],
            "boundingBox": {
                "height": 722.5,
                "width": 389.13488372093025,
                "left": 606.8651162790698,
                "top": 18.53281853281853
            },
            "points": [
                {
                    "x": 606.8651162790698,
                    "y": 18.53281853281853
                },
                {
                    "x": 996,
                    "y": 18.53281853281853
                },
                {
                    "x": 996,
                    "y": 741.0328185328185
                },
                {
                    "x": 606.8651162790698,
                    "y": 741.0328185328185
                }
            ]
        },
        {
            "id": "CTxZiPZDKUk",
            "type": "RECTANGLE",
            "tags": [
                "shout_bubble"
            ],
            "boundingBox": {
                "left": 210,
                "top": 790,
                "width": 317.5,
                "height": 672.5
            },
            "points": [
                {
                    "x": 210,
                    "y": 790
                },
                {
                    "x": 527.5,
                    "y": 790
                },
                {
                    "x": 527.5,
                    "y": 1462.5
                },
                {
                    "x": 210,
                    "y": 1462.5
                }
            ]
        },
        {
            "id": "T5wAARn1y1",
            "type": "RECTANGLE",
            "tags": [
                "shout_bubble"
            ],
            "boundingBox": {
                "height": 551.3513513513514,
                "width": 316.5581395348837,
                "left": 540.4168604651163,
                "top": 976.0617760617761
            },
            "points": [
                {
                    "x": 540.4168604651163,
                    "y": 976.0617760617761
                },
                {
                    "x": 856.975,
                    "y": 976.0617760617761
                },
                {
                    "x": 856.975,
                    "y": 1527.4131274131275
                },
                {
                    "x": 540.4168604651163,
                    "y": 1527.4131274131275
                }
            ]
        }
    ],
    "version": "2.2.0"
}