{
    "asset": {
        "format": "jpg",
        "id": "konepunch_man_143_026_jpg.rf.8f00b16173657be7f89c0a4eeb653625",
        "name": "konepunch_man_143_026_jpg.rf.8f00b16173657be7f89c0a4eeb653625.jpg",
        "path": "file:C:\\Users\\asus\\source\\repos\\MangaKB\\MangaKB\\MangaDataS\\vott-json-export\\konepunch_man_143_026_jpg.rf.8f00b16173657be7f89c0a4eeb653625.jpg",
        "size": {
            "width": 500,
            "height": 1000
        },
        "state": 2,
        "type": 1
    },
    "regions": [
        {
            "id": "zU1B0VujCX",
            "type": "RECTANGLE",
            "tags": [
                "shout_bubble"
            ],
            "boundingBox": {
                "left": 34,
                "top": 145,
                "width": 113,
                "height": 262
            },
            "points": [
                {
                    "x": 34,
                    "y": 145
                },
                {
                    "x": 147,
                    "y": 145
                },
                {
                    "x": 147,
                    "y": 407
                },
                {
                    "x": 34,
                    "y": 407
                }
            ]
        },
        {
            "id": "539D-pqR1UK",
            "type": "RECTANGLE",
            "tags": [
                "shout_bubble"
            ],
            "boundingBox": {
                "left": 53,
                "top": 410,
                "width": 36,
                "height": 109
            },
            "points": [
                {
                    "x": 53,
                    "y": 410
                },
                {
                    "x": 89,
                    "y": 410
                },
                {
                    "x": 89,
                    "y": 519
                },
                {
                    "x": 53,
                    "y": 519
                }
            ]
        },
        {
            "id": "Rnj3f18Xzbx",
            "type": "RECTANGLE",
            "tags": [
                "shout_bubble"
            ],
            "boundingBox": {
                "height": 192,
                "width": 58,
                "left": 215.03474903474904,
                "top": 398.03474903474904
            },
            "points": [
                {
                    "x": 215.03474903474904,
                    "y": 398.03474903474904
                },
                {
                    "x": 273.03474903474904,
                    "y": 398.03474903474904
                },
                {
                    "x": 273.03474903474904,
                    "y": 590.0347490347491
                },
                {
                    "x": 215.03474903474904,
                    "y": 590.0347490347491
                }
            ]
        },
        {
            "id": "X5cDaj-h3gZ",
            "type": "RECTANGLE",
            "tags": [
                "shout_bubble"
            ],
            "boundingBox": {
                "left": 381,
                "top": 477,
                "width": 86,
                "height": 184
            },
            "points": [
                {
                    "x": 381,
                    "y": 477
                },
                {
                    "x": 467,
                    "y": 477
                },
                {
                    "x": 467,
                    "y": 661
                },
                {
                    "x": 381,
                    "y": 661
                }
            ]
        },
        {
            "id": "BMK99PeedYY",
            "type": "RECTANGLE",
            "tags": [
                "shout_bubble"
            ],
            "boundingBox": {
                "left": 53,
                "top": 735,
                "width": 81,
                "height": 78
            },
            "points": [
                {
                    "x": 53,
                    "y": 735
                },
                {
                    "x": 134,
                    "y": 735
                },
                {
                    "x": 134,
                    "y": 813
                },
                {
                    "x": 53,
                    "y": 813
                }
            ]
        }
    ],
    "version": "2.2.0"
}