{
    "asset": {
        "format": "jpg",
        "id": "m20180727_95546_0832_jpg.rf.9b7025cba1f298a20961e5fd7ed73916",
        "name": "m20180727_95546_0832_jpg.rf.9b7025cba1f298a20961e5fd7ed73916.jpg",
        "path": "file:C:\\Users\\asus\\source\\repos\\MangaKB\\MangaKB\\MangaDataS\\vott-json-export\\m20180727_95546_0832_jpg.rf.9b7025cba1f298a20961e5fd7ed73916.jpg",
        "size": {
            "width": 484,
            "height": 4096
        },
        "state": 2,
        "type": 1
    },
    "regions": [
        {
            "id": "46500",
            "type": "RECTANGLE",
            "tags": [
                "text_bubble"
            ],
            "boundingBox": {
                "left": 104,
                "top": 3327,
                "width": 277.4,
                "height": 285.95
            },
            "points": [
                {
                    "x": 104,
                    "y": 3327
                },
                {
                    "x": 381.4,
                    "y": 3327
                },
                {
                    "x": 381.4,
                    "y": 3612.95
                },
                {
                    "x": 104,
                    "y": 3612.95
                }
            ]
        }
    ],
    "version": "2.2.0"
}